Workbook

Sheet songs
A1: artist_id | B1: artist_name | C1: song | D1: duration_ms | E1: duration_seconds | F1: explicit | G1: year_id | H1: year | I1: popularity | J1: danceability | K1: energy | L1: energy_category | M1: loudness | N1: speechiness | O1: acousticness | P1: instrumentalness | Q1: liveness | R1: valence | S1: song_mood | T1: tempo | U1: genre
A2: 619 | B2: =_xlfn.xlookup(A2, artists!A$2:A$836, artists!B$2:B$836) -> The Chainsmokers | C2: #SELFIE - Original Mix | D2: 183750 | E2: =D2/1000 -> 183.75 | F2: =FALSE() -> FALSE | G2: 17 | H2: =_xlfn.xlookup(G2, years!A$2:A$836, years!B$2:B$836) -> 2014 | I2: 0 | J2: 0.789 | K2: 0.915 | L2: =IF(K2>0.66,"High",IF(K2>0.33&K2<=0.66,"Medium","Low")) -> High | M2: -3.263 | N2: 0.248 | O2: 0.0135 | P2: 8.77e-06 | Q2: 0.0818 | R2: 0.66 | S2: =IF(R2 >= 0.5, "Positive", "Negative") -> Positive | T2: 127.955 | U2: pop, Dance/Electronic
A3: 404 | B3: =_xlfn.xlookup(A3, artists!A$2:A$836, artists!B$2:B$836) -> will.i.am | C3: #thatPOWER | D3: 279506 | E3: =D3/1000 -> 279.506 | F3: =FALSE() -> FALSE | G3: 16 | H3: =_xlfn.xlookup(G3, years!A$2:A$836, years!B$2:B$836) -> 2013 | I3: 68 | J3: 0.797 | K3: 0.608 | L3: =IF(K3>0.66,"High",IF(K3>0.33&K3<=0.66,"Medium","Low")) -> Low | M3: -6.096 | N3: 0.0584 | O3: 0.00112 | P3: 7.66e-05 | Q3: 0.0748 | R3: 0.402 | S3: =IF(R3 >= 0.5, "Positive", "Negative") -> Negative | T3: 127.999 | U3: hip hop, pop
A4: 169 | B4: =_xlfn.xlookup(A4, artists!A$2:A$836, artists!B$2:B$836) -> Sean Paul | C4: (When You Gonna) Give It Up to Me (feat. Keyshia Cole) - Radio Version | D4: 243880 | E4: =D4/1000 -> 243.88 | F4: =FALSE() -> FALSE | G4: 9 | H4: =_xlfn.xlookup(G4, years!A$2:A$836, years!B$2:B$836) -> 2006 | I4: 58 | J4: 0.711 | K4: 0.761 | L4: =IF(K4>0.66,"High",IF(K4>0.33&K4<=0.66,"Medium","Low")) -> High | M4: -3.04 | N4: 0.225 | O4: 0.067 | P4: 0 | Q4: 0.041 | R4: 0.718 | S4: =IF(R4 >= 0.5, "Positive", "Negative") -> Positive | T4: 95.824 | U4: hip hop, pop
A5: 669 | B5: =_xlfn.xlookup(A5, artists!A$2:A$836, artists!B$2:B$836) -> Tame Impala | C5: The Less I Know The Better | D5: 216320 | E5: =D5/1000 -> 216.32 | F5: =TRUE() -> TRUE | G5: 18 | H5: =_xlfn.xlookup(G5, years!A$2:A$836, years!B$2:B$836) -> 2015 | I5: 83 | J5: 0.64 | K5: 0.74 | L5: =IF(K5>0.66,"High",IF(K5>0.33&K5<=0.66,"Medium","Low")) -> High | M5: -4.083 | N5: 0.0284 | O5: 0.0115 | P5: 0.00678 | Q5: 0.167 | R5: 0.785 | S5: =IF(R5 >= 0.5, "Positive", "Negative") -> Positive | T5: 116.879 | U5: metal
A6: 35 | B6: =_xlfn.xlookup(A6, artists!A$2:A$836, artists!B$2:B$836) -> JAY-Z | C6: 03' Bonnie & Clyde | D6: 205560 | E6: =D6/1000 -> 205.56 | F6: =TRUE() -> TRUE | G6: 5 | H6: =_xlfn.xlookup(G6, years!A$2:A$836, years!B$2:B$836) -> 2002 | I6: 71 | J6: 0.759 | K6: 0.678 | L6: =IF(K6>0.66,"High",IF(K6>0.33&K6<=0.66,"Medium","Low")) -> High | M6: -5.148 | N6: 0.314 | O6: 0.23 | P6: 0 | Q6: 0.15 | R6: 0.327 | S6: =IF(R6 >= 0.5, "Positive", "Negative") -> Negative | T6: 89.64 | U6: hip hop
A7: 301 | B7: =_xlfn.xlookup(A7, artists!A$2:A$836, artists!B$2:B$836) -> Amerie | C7: 1 Thing | D7: 238746 | E7: =D7/1000 -> 238.746 | F7: =FALSE() -> FALSE | G7: 11 | H7: =_xlfn.xlookup(G7, years!A$2:A$836, years!B$2:B$836) -> 2008 | I7: 52 | J7: 0.636 | K7: 0.946 | L7: =IF(K7>0.66,"High",IF(K7>0.33&K7<=0.66,"Medium","Low")) -> High | M7: -4.683 | N7: 0.332 | O7: 0.115 | P7: 3.75e-05 | Q7: 0.0416 | R7: 0.891 | S7: =IF(R7 >= 0.5, "Positive", "Negative") -> Positive | T7: 125.085 | U7: hip hop, pop, R&B
A8: 249 | B8: =_xlfn.xlookup(A8, artists!A$2:A$836, artists!B$2:B$836) -> Ciara | C8: 1, 2 Step (feat. Missy Elliott) - Main | D8: 202213 | E8: =D8/1000 -> 202.213 | F8: =FALSE() -> FALSE | G8: 8 | H8: =_xlfn.xlookup(G8, years!A$2:A$836, years!B$2:B$836) -> 2005 | I8: 52 | J8: 0.939 | K8: 0.498 | L8: =IF(K8>0.66,"High",IF(K8>0.33&K8<=0.66,"Medium","Low")) -> Low | M8: -10.94 | N8: 0.161 | O8: 0.0444 | P8: 0.00128 | Q8: 0.0475 | R8: 0.801 | S8: =IF(R8 >= 0.5, "Positive", "Negative") -> Positive | T8: 113.053 | U8: pop, R&B
A9: 180 | B9: =_xlfn.xlookup(A9, artists!A$2:A$836, artists!B$2:B$836) -> Coldplay | C9: Hymn for the Weekend | D9: 258266 | E9: =D9/1000 -> 258.266 | F9: =FALSE() -> FALSE | G9: 18 | H9: =_xlfn.xlookup(G9, years!A$2:A$836, years!B$2:B$836) -> 2015 | I9: 82 | J9: 0.491 | K9: 0.693 | L9: =IF(K9>0.66,"High",IF(K9>0.33&K9<=0.66,"Medium","Low")) -> High | M9: -6.487 | N9: 0.0377 | O9: 0.211 | P9: 6.92e-06 | Q9: 0.325 | R9: 0.412 | S9: =IF(R9 >= 0.5, "Positive", "Negative") -> Negative | T9: 90.027 | U9: rock, pop
A10: 781 | B10: =_xlfn.xlookup(A10, artists!A$2:A$836, artists!B$2:B$836) -> MK | C10: 17 | D10: 196489 | E10: =D10/1000 -> 196.489 | F10: =FALSE() -> FALSE | G10: 20 | H10: =_xlfn.xlookup(G10, years!A$2:A$836, years!B$2:B$836) -> 2017 | I10: 65 | J10: 0.703 | K10: 0.832 | L10: =IF(K10>0.66,"High",IF(K10>0.33&K10<=0.66,"Medium","Low")) -> High | M10: -7.202 | N10: 0.0689 | O10: 0.00149 | P10: 0.127 | Q10: 0.0696 | R10: 0.667 | S10: =IF(R10 >= 0.5, "Positive", "Negative") -> Positive | T10: 122.029 | U10: pop, Dance/Electronic
A11: 714 | B11: =_xlfn.xlookup(A11, artists!A$2:A$836, artists!B$2:B$836) -> Hilltop Hoods | C11: 1955 | D11: 239280 | E11: =D11/1000 -> 239.28 | F11: =FALSE() -> FALSE | G11: 19 | H11: =_xlfn.xlookup(G11, years!A$2:A$836, years!B$2:B$836) -> 2016 | I11: 63 | J11: 0.766 | K11: 0.5 | L11: =IF(K11>0.66,"High",IF(K11>0.33&K11<=0.66,"Medium","Low")) -> Low | M11: -7.558 | N11: 0.0695 | O11: 0.719 | P11: 5.91e-06 | Q11: 0.304 | R11: 0.71 | S11: =IF(R11 >= 0.5, "Positive", "Negative") -> Positive | T11: 84.044 | U11: hip hop, pop
A12: 284 | B12: =_xlfn.xlookup(A12, artists!A$2:A$836, artists!B$2:B$836) -> James Blunt | C12: 1973 | D12: 280026 | E12: =D12/1000 -> 280.026 | F12: =FALSE() -> FALSE | G12: 10 | H12: =_xlfn.xlookup(G12, years!A$2:A$836, years!B$2:B$836) -> 2007 | I12: 68 | J12: 0.72 | K12: 0.668 | L12: =IF(K12>0.66,"High",IF(K12>0.33&K12<=0.66,"Medium","Low")) -> High | M12: -7.928 | N12: 0.0269 | O12: 0.0652 | P12: 0.00664 | Q12: 0.0789 | R12: 0.768 | S12: =IF(R12 >= 0.5, "Positive", "Negative") -> Positive | T12: 123.007 | U12: pop
A13: 611 | B13: =_xlfn.xlookup(A13, artists!A$2:A$836, artists!B$2:B$836) -> Tinashe | C13: 2 On (feat. ScHoolboy Q) | D13: 227000 | E13: =D13/1000 -> 227 | F13: =TRUE() -> TRUE | G13: 17 | H13: =_xlfn.xlookup(G13, years!A$2:A$836, years!B$2:B$836) -> 2014 | I13: 71 | J13: 0.742 | K13: 0.595 | L13: =IF(K13>0.66,"High",IF(K13>0.33&K13<=0.66,"Medium","Low")) -> Low | M13: -7.51 | N13: 0.107 | O13: 0.15 | P13: 0 | Q13: 0.111 | R13: 0.431 | S13: =IF(R13 >= 0.5, "Positive", "Negative") -> Negative | T13: 101.013 | U13: hip hop, pop, R&B, Dance/Electronic
A14: 336 | B14: =_xlfn.xlookup(A14, artists!A$2:A$836, artists!B$2:B$836) -> Fall Out Boy | C14: Centuries | D14: 228360 | E14: =D14/1000 -> 228.36 | F14: =FALSE() -> FALSE | G14: 18 | H14: =_xlfn.xlookup(G14, years!A$2:A$836, years!B$2:B$836) -> 2015 | I14: 80 | J14: 0.393 | K14: 0.858 | L14: =IF(K14>0.66,"High",IF(K14>0.33&K14<=0.66,"Medium","Low")) -> High | M14: -2.868 | N14: 0.0729 | O14: 0.00359 | P14: 0 | Q14: 0.102 | R14: 0.56 | S14: =IF(R14 >= 0.5, "Positive", "Negative") -> Positive | T14: 176.042 | U14: rock
A15: 698 | B15: =_xlfn.xlookup(A15, artists!A$2:A$836, artists!B$2:B$836) -> Anne-Marie | C15: 2002 | D15: 186986 | E15: =D15/1000 -> 186.986 | F15: =FALSE() -> FALSE | G15: 21 | H15: =_xlfn.xlookup(G15, years!A$2:A$836, years!B$2:B$836) -> 2018 | I15: 80 | J15: 0.697 | K15: 0.683 | L15: =IF(K15>0.66,"High",IF(K15>0.33&K15<=0.66,"Medium","Low")) -> High | M15: -2.881 | N15: 0.117 | O15: 0.0372 | P15: 0 | Q15: 0.137 | R15: 0.603 | S15: =IF(R15 >= 0.5, "Positive", "Negative") -> Positive | T15: 96.133 | U15: pop, Dance/Electronic
A16: 271 | B16: =_xlfn.xlookup(A16, artists!A$2:A$836, artists!B$2:B$836) -> Green Day | C16: 21 Guns | D16: 321093 | E16: =D16/1000 -> 321.093 | F16: =FALSE() -> FALSE | G16: 12 | H16: =_xlfn.xlookup(G16, years!A$2:A$836, years!B$2:B$836) -> 2009 | I16: 73 | J16: 0.268 | K16: 0.742 | L16: =IF(K16>0.66,"High",IF(K16>0.33&K16<=0.66,"Medium","Low")) -> High | M16: -4.939 | N16: 0.0355 | O16: 0.0518 | P16: 0 | Q16: 0.626 | R16: 0.416 | S16: =IF(R16 >= 0.5, "Positive", "Negative") -> Negative | T16: 159.779 | U16: rock
A17: 191 | B17: =_xlfn.xlookup(A17, artists!A$2:A$836, artists!B$2:B$836) -> 50 Cent | C17: 21 Questions | D17: 224440 | E17: =D17/1000 -> 224.44 | F17: =TRUE() -> TRUE | G17: 6 | H17: =_xlfn.xlookup(G17, years!A$2:A$836, years!B$2:B$836) -> 2003 | I17: 72 | J17: 0.646 | K17: 0.813 | L17: =IF(K17>0.66,"High",IF(K17>0.33&K17<=0.66,"Medium","Low")) -> High | M17: -3.846 | N17: 0.299 | O17: 0.349 | P17: 9.37e-05 | Q17: 0.0427 | R17: 0.895 | S17: =IF(R17 >= 0.5, "Positive", "Negative") -> Positive | T17: 92.729 | U17: hip hop, pop
A18: 135 | B18: =_xlfn.xlookup(A18, artists!A$2:A$836, artists!B$2:B$836) -> So Solid Crew | C18: 21 Seconds | D18: 302826 | E18: =D18/1000 -> 302.826 | F18: =TRUE() -> TRUE | G18: 4 | H18: =_xlfn.xlookup(G18, years!A$2:A$836, years!B$2:B$836) -> 2001 | I18: 51 | J18: 0.607 | K18: 0.637 | L18: =IF(K18>0.66,"High",IF(K18>0.33&K18<=0.66,"Medium","Low")) -> Low | M18: -11.072 | N18: 0.241 | O18: 0.0191 | P18: 0 | Q18: 0.124 | R18: 0.818 | S18: =IF(R18 >= 0.5, "Positive", "Negative") -> Positive | T18: 137.03 | U18: Dance/Electronic
A19: 545 | B19: =_xlfn.xlookup(A19, artists!A$2:A$836, artists!B$2:B$836) -> Azealia Banks | C19: 212 | D19: 204956 | E19: =D19/1000 -> 204.956 | F19: =TRUE() -> TRUE | G19: 17 | H19: =_xlfn.xlookup(G19, years!A$2:A$836, years!B$2:B$836) -> 2014 | I19: 0 | J19: 0.847 | K19: 0.769 | L19: =IF(K19>0.66,"High",IF(K19>0.33&K19<=0.66,"Medium","Low")) -> High | M19: -5.761 | N19: 0.258 | O19: 0.0145 | P19: 0.00012 | Q19: 0.0767 | R19: 0.626 | S19: =IF(R19 >= 0.5, "Positive", "Negative") -> Positive | T19: 126.017 | U19: hip hop, pop, R&B
A20: 439 | B20: =_xlfn.xlookup(A20, artists!A$2:A$836, artists!B$2:B$836) -> Taylor Swift | C20: 22 | D20: 232120 | E20: =D20/1000 -> 232.12 | F20: =FALSE() -> FALSE | G20: 15 | H20: =_xlfn.xlookup(G20, years!A$2:A$836, years!B$2:B$836) -> 2012 | I20: 68 | J20: 0.661 | K20: 0.729 | L20: =IF(K20>0.66,"High",IF(K20>0.33&K20<=0.66,"Medium","Low")) -> High | M20: -6.561 | N20: 0.0376 | O20: 0.00215 | P20: 0.0013 | Q20: 0.0477 | R20: 0.668 | S20: =IF(R20 >= 0.5, "Positive", "Negative") -> Positive | T20: 103.987 | U20: pop
A21: 651 | B21: =_xlfn.xlookup(A21, artists!A$2:A$836, artists!B$2:B$836) -> Twenty One Pilots | C21: Ride | D21: 214506 | E21: =D21/1000 -> 214.506 | F21: =FALSE() -> FALSE | G21: 18 | H21: =_xlfn.xlookup(G21, years!A$2:A$836, years!B$2:B$836) -> 2015 | I21: 80 | J21: 0.645 | K21: 0.713 | L21: =IF(K21>0.66,"High",IF(K21>0.33&K21<=0.66,"Medium","Low")) -> High | M21: -5.355 | N21: 0.0393 | O21: 0.00835 | P21: 0 | Q21: 0.113 | R21: 0.566 | S21: =IF(R21 >= 0.5, "Positive", "Negative") -> Positive | T21: 74.989 | U21: rock
A22: 438 | B22: =_xlfn.xlookup(A22, artists!A$2:A$836, artists!B$2:B$836) -> David Guetta | C22: 2U (feat. Justin Bieber) | D22: 194896 | E22: =D22/1000 -> 194.896 | F22: =FALSE() -> FALSE | G22: 20 | H22: =_xlfn.xlookup(G22, years!A$2:A$836, years!B$2:B$836) -> 2017 | I22: 67 | J22: 0.548 | K22: 0.65 | L22: =IF(K22>0.66,"High",IF(K22>0.33&K22<=0.66,"Medium","Low")) -> Low | M22: -5.827 | N22: 0.0591 | O22: 0.219 | P22: 0 | Q22: 0.225 | R22: 0.557 | S22: =IF(R22 >= 0.5, "Positive", "Negative") -> Positive | T22: 144.937 | U22: hip hop, pop, Dance/Electronic
A23: 827 | B23: =_xlfn.xlookup(A23, artists!A$2:A$836, artists!B$2:B$836) -> Dominic Fike | C23: 3 Nights | D23: 177666 | E23: =D23/1000 -> 177.666 | F23: =FALSE() -> FALSE | G23: 21 | H23: =_xlfn.xlookup(G23, years!A$2:A$836, years!B$2:B$836) -> 2018 | I23: 78 | J23: 0.815 | K23: 0.518 | L23: =IF(K23>0.66,"High",IF(K23>0.33&K23<=0.66,"Medium","Low")) -> Low | M23: -6.594 | N23: 0.0897 | O23: 0.223 | P23: 0 | Q23: 0.104 | R23: 0.877 | S23: =IF(R23 >= 0.5, "Positive", "Negative") -> Positive | T23: 151.891 | U23: rock, pop
A24: 598 | B24: =_xlfn.xlookup(A24, artists!A$2:A$836, artists!B$2:B$836) -> Childish Gambino | C24: 3005 | D24: 235662 | E24: =D24/1000 -> 235.662 | F24: =TRUE() -> TRUE | G24: 16 | H24: =_xlfn.xlookup(G24, years!A$2:A$836, years!B$2:B$836) -> 2013 | I24: 0 | J24: 0.681 | K24: 0.463 | L24: =IF(K24>0.66,"High",IF(K24>0.33&K24<=0.66,"Medium","Low")) -> Low | M24: -6.542 | N24: 0.289 | O24: 0.128 | P24: 0 | Q24: 0.0769 | R24: 0.661 | S24: =IF(R24 >= 0.5, "Positive", "Negative") -> Positive | T24: 82.92 | U24: hip hop
A25: 31 | B25: =_xlfn.xlookup(A25, artists!A$2:A$836, artists!B$2:B$836) -> Madonna | C25: 4 Minutes (feat. Justin Timberlake & Timbaland) | D25: 189693 | E25: =D25/1000 -> 189.693 | F25: =FALSE() -> FALSE | G25: 12 | H25: =_xlfn.xlookup(G25, years!A$2:A$836, years!B$2:B$836) -> 2009 | I25: 71 | J25: 0.753 | K25: 0.931 | L25: =IF(K25>0.66,"High",IF(K25>0.33&K25<=0.66,"Medium","Low")) -> High | M25: -4.922 | N25: 0.0652 | O25: 0.00994 | P25: 0.00696 | Q25: 0.234 | R25: 0.767 | S25: =IF(R25 >= 0.5, "Positive", "Negative") -> Positive | T25: 113.029 | U25: pop
A26: 41 | B26: =_xlfn.xlookup(A26, artists!A$2:A$836, artists!B$2:B$836) -> Missy Elliott | C26: 4 My People (feat. Eve) | D26: 289373 | E26: =D26/1000 -> 289.373 | F26: =TRUE() -> TRUE | G26: 4 | H26: =_xlfn.xlookup(G26, years!A$2:A$836, years!B$2:B$836) -> 2001 | I26: 49 | J26: 0.969 | K26: 0.701 | L26: =IF(K26>0.66,"High",IF(K26>0.33&K26<=0.66,"Medium","Low")) -> High | M26: -7.503 | N26: 0.156 | O26: 0.14 | P26: 0.00161 | Q26: 0.201 | R26: 0.905 | S26: =IF(R26 >= 0.5, "Positive", "Negative") -> Positive | T26: 121.392 | U26: hip hop, pop, R&B
A27: 402 | B27: =_xlfn.xlookup(A27, artists!A$2:A$836, artists!B$2:B$836) -> Lil Wayne | C27: 6 Foot 7 Foot | D27: 248586 | E27: =D27/1000 -> 248.586 | F27: =TRUE() -> TRUE | G27: 14 | H27: =_xlfn.xlookup(G27, years!A$2:A$836, years!B$2:B$836) -> 2011 | I27: 1 | J27: 0.364 | K27: 0.752 | L27: =IF(K27>0.66,"High",IF(K27>0.33&K27<=0.66,"Medium","Low")) -> High | M27: -5.429 | N27: 0.304 | O27: 0.0007 | P27: 0 | Q27: 0.318 | R27: 0.606 | S27: =IF(R27 >= 0.5, "Positive", "Negative") -> Positive | T27: 79.119 | U27: hip hop, pop
A28: 664 | B28: =_xlfn.xlookup(A28, artists!A$2:A$836, artists!B$2:B$836) -> Fetty Wap | C28: 679 (feat. Remy Boyz) | D28: 196693 | E28: =D28/1000 -> 196.693 | F28: =TRUE() -> TRUE | G28: 18 | H28: =_xlfn.xlookup(G28, years!A$2:A$836, years!B$2:B$836) -> 2015 | I28: 74 | J28: 0.618 | K28: 0.717 | L28: =IF(K28>0.66,"High",IF(K28>0.33&K28<=0.66,"Medium","Low")) -> High | M28: -5.738 | N28: 0.318 | O28: 0.00256 | P28: 0 | Q28: 0.625 | R28: 0.603 | S28: =IF(R28 >= 0.5, "Positive", "Negative") -> Positive | T28: 190.05 | U28: hip hop, pop
A29: 56 | B29: =_xlfn.xlookup(A29, artists!A$2:A$836, artists!B$2:B$836) -> Craig David | C29: 7 Days | D29: 235133 | E29: =D29/1000 -> 235.133 | F29: =FALSE() -> FALSE | G29: 3 | H29: =_xlfn.xlookup(G29, years!A$2:A$836, years!B$2:B$836) -> 2000 | I29: 70 | J29: 0.659 | K29: 0.812 | L29: =IF(K29>0.66,"High",IF(K29>0.33&K29<=0.66,"Medium","Low")) -> High | M29: -7.499 | N29: 0.0487 | O29: 0.23 | P29: 0 | Q29: 0.0951 | R29: 0.888 | S29: =IF(R29 >= 0.5, "Positive", "Negative") -> Positive | T29: 83.014 | U29: hip hop, pop, R&B
A30: 600 | B30: =_xlfn.xlookup(A30, artists!A$2:A$836, artists!B$2:B$836) -> Ariana Grande | C30: 7 rings | D30: 178626 | E30: =D30/1000 -> 178.626 | F30: =TRUE() -> TRUE | G30: 22 | H30: =_xlfn.xlookup(G30, years!A$2:A$836, years!B$2:B$836) -> 2019 | I30: 83 | J30: 0.778 | K30: 0.317 | L30: =IF(K30>0.66,"High",IF(K30>0.33&K30<=0.66,"Medium","Low")) -> Low | M30: -10.732 | N30: 0.334 | O30: 0.592 | P30: 0 | Q30: 0.0881 | R30: 0.327 | S30: =IF(R30 >= 0.5, "Positive", "Negative") -> Negative | T30: 140.048 | U30: pop
A31: 721 | B31: =_xlfn.xlookup(A31, artists!A$2:A$836, artists!B$2:B$836) -> Billie Eilish | C31: bad guy | D31: 194087 | E31: =D31/1000 -> 194.087 | F31: =FALSE() -> FALSE | G31: 22 | H31: =_xlfn.xlookup(G31, years!A$2:A$836, years!B$2:B$836) -> 2019 | I31: 83 | J31: 0.701 | K31: 0.425 | L31: =IF(K31>0.66,"High",IF(K31>0.33&K31<=0.66,"Medium","Low")) -> Low | M31: -10.965 | N31: 0.375 | O31: 0.328 | P31: 0.13 | Q31: 0.1 | R31: 0.562 | S31: =IF(R31 >= 0.5, "Positive", "Negative") -> Positive | T31: 135.128 | U31: pop, Dance/Electronic
A32: 184 | B32: =_xlfn.xlookup(A32, artists!A$2:A$836, artists!B$2:B$836) -> Elvis Presley | C32: A Little Less Conversation - JXL Radio Edit Remix | D32: 211506 | E32: =D32/1000 -> 211.506 | F32: =FALSE() -> FALSE | G32: 5 | H32: =_xlfn.xlookup(G32, years!A$2:A$836, years!B$2:B$836) -> 2002 | I32: 60 | J32: 0.597 | K32: 0.97 | L32: =IF(K32>0.66,"High",IF(K32>0.33&K32<=0.66,"Medium","Low")) -> High | M32: -5.972 | N32: 0.0502 | O32: 0.000385 | P32: 0.205 | Q32: 0.133 | R32: 0.717 | S32: =IF(R32 >= 0.5, "Positive", "Negative") -> Positive | T32: 114.999 | U32: rock, easy listening
A33: 725 | B33: =_xlfn.xlookup(A33, artists!A$2:A$836, artists!B$2:B$836) -> 21 Savage | C33: a lot | D33: 288624 | E33: =D33/1000 -> 288.624 | F33: =TRUE() -> TRUE | G33: 21 | H33: =_xlfn.xlookup(G33, years!A$2:A$836, years!B$2:B$836) -> 2018 | I33: 78 | J33: 0.837 | K33: 0.636 | L33: =IF(K33>0.66,"High",IF(K33>0.33&K33<=0.66,"Medium","Low")) -> Low | M33: -7.643 | N33: 0.086 | O33: 0.0395 | P33: 0.00125 | Q33: 0.342 | R33: 0.274 | S33: =IF(R33 >= 0.5, "Positive", "Negative") -> Negative | T33: 145.972 | U33: hip hop
A34: 402 | B34: =_xlfn.xlookup(A34, artists!A$2:A$836, artists!B$2:B$836) -> Lil Wayne | C34: A Milli | D34: 221840 | E34: =D34/1000 -> 221.84 | F34: =TRUE() -> TRUE | G34: 11 | H34: =_xlfn.xlookup(G34, years!A$2:A$836, years!B$2:B$836) -> 2008 | I34: 69 | J34: 0.674 | K34: 0.695 | L34: =IF(K34>0.66,"High",IF(K34>0.33&K34<=0.66,"Medium","Low")) -> High | M34: -8.636 | N34: 0.278 | O34: 0.0387 | P34: 0.00202 | Q34: 0.194 | R34: 0.773 | S34: =IF(R34 >= 0.5, "Positive", "Negative") -> Positive | T34: 151.486 | U34: hip hop, pop
A35: 337 | B35: =_xlfn.xlookup(A35, artists!A$2:A$836, artists!B$2:B$836) -> Leona Lewis | C35: A Moment Like This | D35: 257293 | E35: =D35/1000 -> 257.293 | F35: =FALSE() -> FALSE | G35: 10 | H35: =_xlfn.xlookup(G35, years!A$2:A$836, years!B$2:B$836) -> 2007 | I35: 57 | J35: 0.261 | K35: 0.562 | L35: =IF(K35>0.66,"High",IF(K35>0.33&K35<=0.66,"Medium","Low")) -> Low | M35: -3.667 | N35: 0.0301 | O35: 0.423 | P35: 7.54e-06 | Q35: 0.131 | R35: 0.167 | S35: =IF(R35 >= 0.5, "Positive", "Negative") -> Negative | T35: 70.543 | U35: pop, R&B
A36: 65 | B36: =_xlfn.xlookup(A36, artists!A$2:A$836, artists!B$2:B$836) -> Céline Dion | C36: A New Day Has Come - Radio Remix | D36: 259773 | E36: =D36/1000 -> 259.773 | F36: =FALSE() -> FALSE | G36: 4 | H36: =_xlfn.xlookup(G36, years!A$2:A$836, years!B$2:B$836) -> 2001 | I36: 59 | J36: 0.574 | K36: 0.691 | L36: =IF(K36>0.66,"High",IF(K36>0.33&K36<=0.66,"Medium","Low")) -> High | M36: -5.103 | N36: 0.035 | O36: 0.0826 | P36: 1.65e-05 | Q36: 0.149 | R36: 0.195 | S36: =IF(R36 >= 0.5, "Positive", "Negative") -> Negative | T36: 91.969 | U36: pop
A37: 180 | B37: =_xlfn.xlookup(A37, artists!A$2:A$836, artists!B$2:B$836) -> Coldplay | C37: A Sky Full of Stars | D37: 267866 | E37: =D37/1000 -> 267.866 | F37: =FALSE() -> FALSE | G37: 17 | H37: =_xlfn.xlookup(G37, years!A$2:A$836, years!B$2:B$836) -> 2014 | I37: 80 | J37: 0.545 | K37: 0.675 | L37: =IF(K37>0.66,"High",IF(K37>0.33&K37<=0.66,"Medium","Low")) -> High | M37: -6.474 | N37: 0.0279 | O37: 0.00617 | P37: 0.00197 | Q37: 0.209 | R37: 0.162 | S37: =IF(R37 >= 0.5, "Positive", "Negative") -> Negative | T37: 124.97 | U37: rock, pop
A38: 147 | B38: =_xlfn.xlookup(A38, artists!A$2:A$836, artists!B$2:B$836) -> Vanessa Carlton | C38: A Thousand Miles | D38: 237493 | E38: =D38/1000 -> 237.493 | F38: =FALSE() -> FALSE | G38: 5 | H38: =_xlfn.xlookup(G38, years!A$2:A$836, years!B$2:B$836) -> 2002 | I38: 75 | J38: 0.56 | K38: 0.825 | L38: =IF(K38>0.66,"High",IF(K38>0.33&K38<=0.66,"Medium","Low")) -> High | M38: -3.862 | N38: 0.0379 | O38: 0.323 | P38: 0 | Q38: 0.161 | R38: 0.268 | S38: =IF(R38 >= 0.5, "Positive", "Negative") -> Negative | T38: 94.931 | U38: Folk/Acoustic, pop
A39: 533 | B39: =_xlfn.xlookup(A39, artists!A$2:A$836, artists!B$2:B$836) -> Christina Perri | C39: A Thousand Years | D39: 285120 | E39: =D39/1000 -> 285.12 | F39: =FALSE() -> FALSE | G39: 14 | H39: =_xlfn.xlookup(G39, years!A$2:A$836, years!B$2:B$836) -> 2011 | I39: 70 | J39: 0.421 | K39: 0.407 | L39: =IF(K39>0.66,"High",IF(K39>0.33&K39<=0.66,"Medium","Low")) -> Low | M39: -7.445 | N39: 0.0267 | O39: 0.309 | P39: 0.000961 | Q39: 0.11 | R39: 0.161 | S39: =IF(R39 >= 0.5, "Positive", "Negative") -> Negative | T39: 139.028 | U39: pop
A40: 179 | B40: =_xlfn.xlookup(A40, artists!A$2:A$836, artists!B$2:B$836) -> Alicia Keys | C40: A Woman's Worth | D40: 303333 | E40: =D40/1000 -> 303.333 | F40: =FALSE() -> FALSE | G40: 4 | H40: =_xlfn.xlookup(G40, years!A$2:A$836, years!B$2:B$836) -> 2001 | I40: 52 | J40: 0.652 | K40: 0.41 | L40: =IF(K40>0.66,"High",IF(K40>0.33&K40<=0.66,"Medium","Low")) -> Low | M40: -8.323 | N40: 0.158 | O40: 0.333 | P40: 0 | Q40: 0.064 | R40: 0.495 | S40: =IF(R40 >= 0.5, "Positive", "Negative") -> Negative | T40: 75.09 | U40: pop, R&B
A41: 719 | B41: =_xlfn.xlookup(A41, artists!A$2:A$836, artists!B$2:B$836) -> Luis Fonsi | C41: Ã‰chame La Culpa | D41: 173720 | E41: =D41/1000 -> 173.72 | F41: =FALSE() -> FALSE | G41: 20 | H41: =_xlfn.xlookup(G41, years!A$2:A$836, years!B$2:B$836) -> 2017 | I41: 62 | J41: 0.733 | K41: 0.892 | L41: =IF(K41>0.66,"High",IF(K41>0.33&K41<=0.66,"Medium","Low")) -> High | M41: -3.641 | N41: 0.0417 | O41: 0.0376 | P41: 0 | Q41: 0.137 | R41: 0.675 | S41: =IF(R41 >= 0.5, "Positive", "Negative") -> Positive | T41: 95.989 | U41: pop, latin
A42: 156 | B42: =_xlfn.xlookup(A42, artists!A$2:A$836, artists!B$2:B$836) -> Sugababes | C42: About You Now | D42: 212400 | E42: =D42/1000 -> 212.4 | F42: =FALSE() -> FALSE | G42: 10 | H42: =_xlfn.xlookup(G42, years!A$2:A$836, years!B$2:B$836) -> 2007 | I42: 66 | J42: 0.584 | K42: 0.699 | L42: =IF(K42>0.66,"High",IF(K42>0.33&K42<=0.66,"Medium","Low")) -> High | M42: -6.065 | N42: 0.0378 | O42: 6.52e-05 | P42: 6.05e-05 | Q42: 0.486 | R42: 0.585 | S42: =IF(R42 >= 0.5, "Positive", "Negative") -> Positive | T42: 82.499 | U42: pop, R&B
A43: 372 | B43: =_xlfn.xlookup(A43, artists!A$2:A$836, artists!B$2:B$836) -> Calvin Harris | C43: Acceptable in the 80's | D43: 333680 | E43: =D43/1000 -> 333.68 | F43: =FALSE() -> FALSE | G43: 10 | H43: =_xlfn.xlookup(G43, years!A$2:A$836, years!B$2:B$836) -> 2007 | I43: 57 | J43: 0.787 | K43: 0.808 | L43: =IF(K43>0.66,"High",IF(K43>0.33&K43<=0.66,"Medium","Low")) -> High | M43: -5.454 | N43: 0.0511 | O43: 0.0143 | P43: 0.257 | Q43: 0.0466 | R43: 0.942 | S43: =IF(R43 >= 0.5, "Positive", "Negative") -> Positive | T43: 127.99 | U43: hip hop, pop, Dance/Electronic
A44: 808 | B44: =_xlfn.xlookup(A44, artists!A$2:A$836, artists!B$2:B$836) -> Paulo Londra | C44: Adan y Eva | D44: 256971 | E44: =D44/1000 -> 256.971 | F44: =FALSE() -> FALSE | G44: 22 | H44: =_xlfn.xlookup(G44, years!A$2:A$836, years!B$2:B$836) -> 2019 | I44: 72 | J44: 0.767 | K44: 0.709 | L44: =IF(K44>0.66,"High",IF(K44>0.33&K44<=0.66,"Medium","Low")) -> High | M44: -4.47 | N44: 0.336 | O44: 0.323 | P44: 0 | Q44: 0.0745 | R44: 0.72 | S44: =IF(R44 >= 0.5, "Positive", "Negative") -> Positive | T44: 171.993 | U44: hip hop, latin, Dance/Electronic
A45: 413 | B45: =_xlfn.xlookup(A45, artists!A$2:A$836, artists!B$2:B$836) -> Saving Abel | C45: Addicted | D45: 222826 | E45: =D45/1000 -> 222.826 | F45: =TRUE() -> TRUE | G45: 11 | H45: =_xlfn.xlookup(G45, years!A$2:A$836, years!B$2:B$836) -> 2008 | I45: 69 | J45: 0.512 | K45: 0.864 | L45: =IF(K45>0.66,"High",IF(K45>0.33&K45<=0.66,"Medium","Low")) -> High | M45: -4.146 | N45: 0.0338 | O45: 0.000821 | P45: 0 | Q45: 0.0982 | R45: 0.527 | S45: =IF(R45 >= 0.5, "Positive", "Negative") -> Positive | T45: 138.018 | U45: rock, metal
A46: 150 | B46: =_xlfn.xlookup(A46, artists!A$2:A$836, artists!B$2:B$836) -> Truth Hurts | C46: Addictive | D46: 226440 | E46: =D46/1000 -> 226.44 | F46: =TRUE() -> TRUE | G46: 5 | H46: =_xlfn.xlookup(G46, years!A$2:A$836, years!B$2:B$836) -> 2002 | I46: 58 | J46: 0.701 | K46: 0.677 | L46: =IF(K46>0.66,"High",IF(K46>0.33&K46<=0.66,"Medium","Low")) -> High | M46: -6.591 | N46: 0.147 | O46: 0.0737 | P46: 0.000162 | Q46: 0.187 | R46: 0.367 | S46: =IF(R46 >= 0.5, "Positive", "Negative") -> Negative | T46: 99.271 | U46: pop, R&B
A47: 463 | B47: =_xlfn.xlookup(A47, artists!A$2:A$836, artists!B$2:B$836) -> Justin Bieber | C47: Sorry | D47: 200786 | E47: =D47/1000 -> 200.786 | F47: =FALSE() -> FALSE | G47: 18 | H47: =_xlfn.xlookup(G47, years!A$2:A$836, years!B$2:B$836) -> 2015 | I47: 80 | J47: 0.654 | K47: 0.76 | L47: =IF(K47>0.66,"High",IF(K47>0.33&K47<=0.66,"Medium","Low")) -> High | M47: -3.669 | N47: 0.045 | O47: 0.0797 | P47: 0 | Q47: 0.299 | R47: 0.41 | S47: =IF(R47 >= 0.5, "Positive", "Negative") -> Negative | T47: 99.945 | U47: pop
A48: 129 | B48: =_xlfn.xlookup(A48, artists!A$2:A$836, artists!B$2:B$836) -> Lenny Kravitz | C48: Again | D48: 231666 | E48: =D48/1000 -> 231.666 | F48: =FALSE() -> FALSE | G48: 3 | H48: =_xlfn.xlookup(G48, years!A$2:A$836, years!B$2:B$836) -> 2000 | I48: 68 | J48: 0.55 | K48: 0.804 | L48: =IF(K48>0.66,"High",IF(K48>0.33&K48<=0.66,"Medium","Low")) -> High | M48: -5.218 | N48: 0.0271 | O48: 0.0148 | P48: 4.33e-05 | Q48: 0.105 | R48: 0.789 | S48: =IF(R48 >= 0.5, "Positive", "Negative") -> Positive | T48: 79.166 | U48: rock, pop
A49: 50 | B49: =_xlfn.xlookup(A49, artists!A$2:A$836, artists!B$2:B$836) -> Mariah Carey | C49: Against All Odds (Take A Look at Me Now) (feat. Westlife) | D49: 199480 | E49: =D49/1000 -> 199.48 | F49: =FALSE() -> FALSE | G49: 14 | H49: =_xlfn.xlookup(G49, years!A$2:A$836, years!B$2:B$836) -> 2011 | I49: 0 | J49: 0.471 | K49: 0.514 | L49: =IF(K49>0.66,"High",IF(K49>0.33&K49<=0.66,"Medium","Low")) -> Low | M49: -5.599 | N49: 0.0315 | O49: 0.584 | P49: 0 | Q49: 0.103 | R49: 0.373 | S49: =IF(R49 >= 0.5, "Positive", "Negative") -> Negative | T49: 117.338 | U49: pop, R&B
A50: 547 | B50: =_xlfn.xlookup(A50, artists!A$2:A$836, artists!B$2:B$836) -> Michel Teló | C50: Ai Se Eu Te Pego - Live | D50: 166866 | E50: =D50/1000 -> 166.866 | F50: =FALSE() -> FALSE | G50: 15 | H50: =_xlfn.xlookup(G50, years!A$2:A$836, years!B$2:B$836) -> 2012 | I50: 0 | J50: 0.676 | K50: 0.935 | L50: =IF(K50>0.66,"High",IF(K50>0.33&K50<=0.66,"Medium","Low")) -> High | M50: -4.55 | N50: 0.0692 | O50: 0.357 | P50: 0 | Q50: 0.853 | R50: 0.85 | S50: =IF(R50 >= 0.5, "Positive", "Negative") -> Positive | T50: 96.055 | U50: country, latin
A51: 100 | B51: =_xlfn.xlookup(A51, artists!A$2:A$836, artists!B$2:B$836) -> Jennifer Lopez | C51: Ain't It Funny | D51: 246160 | E51: =D51/1000 -> 246.16 | F51: =FALSE() -> FALSE | G51: 4 | H51: =_xlfn.xlookup(G51, years!A$2:A$836, years!B$2:B$836) -> 2001 | I51: 0 | J51: 0.707 | K51: 0.869 | L51: =IF(K51>0.66,"High",IF(K51>0.33&K51<=0.66,"Medium","Low")) -> High | M51: -4.525 | N51: 0.0481 | O51: 0.104 | P51: 0.000121 | Q51: 0.0813 | R51: 0.621 | S51: =IF(R51 >= 0.5, "Positive", "Negative") -> Positive | T51: 99.825 | U51: hip hop, pop, R&B
A52: 644 | B52: =_xlfn.xlookup(A52, artists!A$2:A$836, artists!B$2:B$836) -> The Weeknd | C52: Can't Feel My Face | D52: 213520 | E52: =D52/1000 -> 213.52 | F52: =FALSE() -> FALSE | G52: 18 | H52: =_xlfn.xlookup(G52, years!A$2:A$836, years!B$2:B$836) -> 2015 | I52: 79 | J52: 0.705 | K52: 0.769 | L52: =IF(K52>0.66,"High",IF(K52>0.33&K52<=0.66,"Medium","Low")) -> High | M52: -5.526 | N52: 0.0425 | O52: 0.113 | P52: 0 | Q52: 0.105 | R52: 0.583 | S52: =IF(R52 >= 0.5, "Positive", "Negative") -> Positive | T52: 107.949 | U52: pop, R&B
A53: 57 | B53: =_xlfn.xlookup(A53, artists!A$2:A$836, artists!B$2:B$836) -> Christina Aguilera | C53: Ain't No Other Man | D53: 228906 | E53: =D53/1000 -> 228.906 | F53: =FALSE() -> FALSE | G53: 9 | H53: =_xlfn.xlookup(G53, years!A$2:A$836, years!B$2:B$836) -> 2006 | I53: 63 | J53: 0.862 | K53: 0.742 | L53: =IF(K53>0.66,"High",IF(K53>0.33&K53<=0.66,"Medium","Low")) -> High | M53: -4.722 | N53: 0.222 | O53: 0.00376 | P53: 0.00855 | Q53: 0.103 | R53: 0.511 | S53: =IF(R53 >= 0.5, "Positive", "Negative") -> Positive | T53: 127.91 | U53: pop
A54: 655 | B54: =_xlfn.xlookup(A54, artists!A$2:A$836, artists!B$2:B$836) -> Felix Jaehn | C54: Ain't Nobody (Loves Me Better) (feat. Jasmine Thompson) | D54: 186146 | E54: =D54/1000 -> 186.146 | F54: =FALSE() -> FALSE | G54: 21 | H54: =_xlfn.xlookup(G54, years!A$2:A$836, years!B$2:B$836) -> 2018 | I54: 72 | J54: 0.778 | K54: 0.566 | L54: =IF(K54>0.66,"High",IF(K54>0.33&K54<=0.66,"Medium","Low")) -> Low | M54: -6.959 | N54: 0.0311 | O54: 0.672 | P54: 0.000197 | Q54: 0.0698 | R54: 0.479 | S54: =IF(R54 >= 0.5, "Positive", "Negative") -> Negative | T54: 117.971 | U54: hip hop, pop, Dance/Electronic
A55: 81 | B55: =_xlfn.xlookup(A55, artists!A$2:A$836, artists!B$2:B$836) -> Nelly | C55: Air Force Ones | D55: 304000 | E55: =D55/1000 -> 304 | F55: =TRUE() -> TRUE | G55: 5 | H55: =_xlfn.xlookup(G55, years!A$2:A$836, years!B$2:B$836) -> 2002 | I55: 61 | J55: 0.784 | K55: 0.459 | L55: =IF(K55>0.66,"High",IF(K55>0.33&K55<=0.66,"Medium","Low")) -> Low | M55: -9.74 | N55: 0.317 | O55: 0.0847 | P55: 0 | Q55: 0.079 | R55: 0.618 | S55: =IF(R55 >= 0.5, "Positive", "Negative") -> Positive | T55: 164.062 | U55: hip hop, pop, R&B
A56: 492 | B56: =_xlfn.xlookup(A56, artists!A$2:A$836, artists!B$2:B$836) -> B.o.B | C56: Airplanes (feat. Hayley Williams of Paramore) | D56: 180480 | E56: =D56/1000 -> 180.48 | F56: =TRUE() -> TRUE | G56: 13 | H56: =_xlfn.xlookup(G56, years!A$2:A$836, years!B$2:B$836) -> 2010 | I56: 74 | J56: 0.66 | K56: 0.867 | L56: =IF(K56>0.66,"High",IF(K56>0.33&K56<=0.66,"Medium","Low")) -> High | M56: -4.285 | N56: 0.116 | O56: 0.11 | P56: 0 | Q56: 0.0368 | R56: 0.377 | S56: =IF(R56 >= 0.5, "Positive", "Negative") -> Negative | T56: 93.033 | U56: hip hop, pop
A57: 698 | B57: =_xlfn.xlookup(A57, artists!A$2:A$836, artists!B$2:B$836) -> Anne-Marie | C57: Alarm | D57: 205593 | E57: =D57/1000 -> 205.593 | F57: =TRUE() -> TRUE | G57: 19 | H57: =_xlfn.xlookup(G57, years!A$2:A$836, years!B$2:B$836) -> 2016 | I57: 57 | J57: 0.756 | K57: 0.589 | L57: =IF(K57>0.66,"High",IF(K57>0.33&K57<=0.66,"Medium","Low")) -> Low | M57: -5.093 | N57: 0.232 | O57: 0.0812 | P57: 0 | Q57: 0.176 | R57: 0.811 | S57: =IF(R57 >= 0.5, "Positive", "Negative") -> Positive | T57: 146.928 | U57: pop, Dance/Electronic
A58: 437 | B58: =_xlfn.xlookup(A58, artists!A$2:A$836, artists!B$2:B$836) -> Lady Gaga | C58: Alejandro | D58: 274213 | E58: =D58/1000 -> 274.213 | F58: =FALSE() -> FALSE | G58: 12 | H58: =_xlfn.xlookup(G58, years!A$2:A$836, years!B$2:B$836) -> 2009 | I58: 67 | J58: 0.623 | K58: 0.793 | L58: =IF(K58>0.66,"High",IF(K58>0.33&K58<=0.66,"Medium","Low")) -> High | M58: -6.63 | N58: 0.0462 | O58: 0.000397 | P58: 0.0015 | Q58: 0.375 | R58: 0.36 | S58: =IF(R58 >= 0.5, "Positive", "Negative") -> Negative | T58: 98.998 | U58: pop
A59: 607 | B59: =_xlfn.xlookup(A59, artists!A$2:A$836, artists!B$2:B$836) -> Meghan Trainor | C59: All About That Bass | D59: 187920 | E59: =D59/1000 -> 187.92 | F59: =TRUE() -> TRUE | G59: 18 | H59: =_xlfn.xlookup(G59, years!A$2:A$836, years!B$2:B$836) -> 2015 | I59: 72 | J59: 0.807 | K59: 0.887 | L59: =IF(K59>0.66,"High",IF(K59>0.33&K59<=0.66,"Medium","Low")) -> High | M59: -3.726 | N59: 0.0503 | O59: 0.0573 | P59: 2.87e-06 | Q59: 0.124 | R59: 0.961 | S59: =IF(R59 >= 0.5, "Positive", "Negative") -> Positive | T59: 134.052 | U59: pop
A60: 728 | B60: =_xlfn.xlookup(A60, artists!A$2:A$836, artists!B$2:B$836) -> Jax Jones | C60: All Day And Night | D60: 169303 | E60: =D60/1000 -> 169.303 | F60: =FALSE() -> FALSE | G60: 22 | H60: =_xlfn.xlookup(G60, years!A$2:A$836, years!B$2:B$836) -> 2019 | I60: 60 | J60: 0.585 | K60: 0.782 | L60: =IF(K60>0.66,"High",IF(K60>0.33&K60<=0.66,"Medium","Low")) -> High | M60: -4.101 | N60: 0.0897 | O60: 0.269 | P60: 0 | Q60: 0.156 | R60: 0.521 | S60: =IF(R60 >= 0.5, "Positive", "Negative") -> Positive | T60: 121.908 | U60: hip hop, pop, Dance/Electronic
A61: 672 | B61: =_xlfn.xlookup(A61, artists!A$2:A$836, artists!B$2:B$836) -> Meek Mill | C61: All Eyes on You (feat. Chris Brown & Nicki Minaj) | D61: 223973 | E61: =D61/1000 -> 223.973 | F61: =TRUE() -> TRUE | G61: 18 | H61: =_xlfn.xlookup(G61, years!A$2:A$836, years!B$2:B$836) -> 2015 | I61: 68 | J61: 0.589 | K61: 0.658 | L61: =IF(K61>0.66,"High",IF(K61>0.33&K61<=0.66,"Medium","Low")) -> Low | M61: -5.288 | N61: 0.203 | O61: 0.0242 | P61: 0 | Q61: 0.118 | R61: 0.251 | S61: =IF(R61 >= 0.5, "Positive", "Negative") -> Negative | T61: 77.521 | U61: hip hop, pop
A62: 269 | B62: =_xlfn.xlookup(A62, artists!A$2:A$836, artists!B$2:B$836) -> Kanye West | C62: All Falls Down | D62: 223506 | E62: =D62/1000 -> 223.506 | F62: =TRUE() -> TRUE | G62: 7 | H62: =_xlfn.xlookup(G62, years!A$2:A$836, years!B$2:B$836) -> 2004 | I62: 80 | J62: 0.657 | K62: 0.734 | L62: =IF(K62>0.66,"High",IF(K62>0.33&K62<=0.66,"Medium","Low")) -> High | M62: -4.832 | N62: 0.484 | O62: 0.149 | P62: 0 | Q62: 0.139 | R62: 0.434 | S62: =IF(R62 >= 0.5, "Positive", "Negative") -> Negative | T62: 91.03 | U62: hip hop
A63: 47 | B63: =_xlfn.xlookup(A63, artists!A$2:A$836, artists!B$2:B$836) -> Janet Jackson | C63: All For You | D63: 329933 | E63: =D63/1000 -> 329.933 | F63: =FALSE() -> FALSE | G63: 4 | H63: =_xlfn.xlookup(G63, years!A$2:A$836, years!B$2:B$836) -> 2001 | I63: 65 | J63: 0.753 | K63: 0.934 | L63: =IF(K63>0.66,"High",IF(K63>0.33&K63<=0.66,"Medium","Low")) -> High | M63: -3.011 | N63: 0.0736 | O63: 0.0174 | P63: 0.065 | Q63: 0.128 | R63: 0.73 | S63: =IF(R63 >= 0.5, "Positive", "Negative") -> Positive | T63: 113.525 | U63: pop, R&B
A64: 490 | B64: =_xlfn.xlookup(A64, artists!A$2:A$836, artists!B$2:B$836) -> DJ Khaled | C64: All I Do Is Win (feat. T-Pain, Ludacris, Snoop Dogg & Rick Ross) | D64: 232506 | E64: =D64/1000 -> 232.506 | F64: =TRUE() -> TRUE | G64: 13 | H64: =_xlfn.xlookup(G64, years!A$2:A$836, years!B$2:B$836) -> 2010 | I64: 51 | J64: 0.544 | K64: 0.781 | L64: =IF(K64>0.66,"High",IF(K64>0.33&K64<=0.66,"Medium","Low")) -> High | M64: -3.616 | N64: 0.189 | O64: 0.014 | P64: 0 | Q64: 0.161 | R64: 0.277 | S64: =IF(R64 >= 0.5, "Positive", "Negative") -> Negative | T64: 150.1 | U64: hip hop, pop
A65: 192 | B65: =_xlfn.xlookup(A65, artists!A$2:A$836, artists!B$2:B$836) -> Beyoncé | C65: Baby Boy (feat. Sean Paul) | D65: 244826 | E65: =D65/1000 -> 244.826 | F65: =FALSE() -> FALSE | G65: 6 | H65: =_xlfn.xlookup(G65, years!A$2:A$836, years!B$2:B$836) -> 2003 | I65: 63 | J65: 0.655 | K65: 0.488 | L65: =IF(K65>0.66,"High",IF(K65>0.33&K65<=0.66,"Medium","Low")) -> Low | M65: -9.17 | N65: 0.22 | O65: 0.0825 | P65: 1.16e-06 | Q65: 0.221 | R65: 0.791 | S65: =IF(R65 >= 0.5, "Positive", "Negative") -> Positive | T65: 91.025 | U65: pop, R&B
A66: 100 | B66: =_xlfn.xlookup(A66, artists!A$2:A$836, artists!B$2:B$836) -> Jennifer Lopez | C66: All I Have (feat. LL Cool J) | D66: 254466 | E66: =D66/1000 -> 254.466 | F66: =FALSE() -> FALSE | G66: 5 | H66: =_xlfn.xlookup(G66, years!A$2:A$836, years!B$2:B$836) -> 2002 | I66: 60 | J66: 0.701 | K66: 0.669 | L66: =IF(K66>0.66,"High",IF(K66>0.33&K66<=0.66,"Medium","Low")) -> High | M66: -5.265 | N66: 0.107 | O66: 0.271 | P66: 0 | Q66: 0.158 | R66: 0.446 | S66: =IF(R66 >= 0.5, "Positive", "Negative") -> Negative | T66: 83.066 | U66: hip hop, pop, R&B
A67: 125 | B67: =_xlfn.xlookup(A67, artists!A$2:A$836, artists!B$2:B$836) -> Mis-Teeq | C67: All I Want - Sunship Radio Edit | D67: 207400 | E67: =D67/1000 -> 207.4 | F67: =FALSE() -> FALSE | G67: 7 | H67: =_xlfn.xlookup(G67, years!A$2:A$836, years!B$2:B$836) -> 2004 | I67: 46 | J67: 0.795 | K67: 0.919 | L67: =IF(K67>0.66,"High",IF(K67>0.33&K67<=0.66,"Medium","Low")) -> High | M67: -3.07 | N67: 0.0835 | O67: 0.37 | P67: 0.00863 | Q67: 0.189 | R67: 0.96 | S67: =IF(R67 >= 0.5, "Positive", "Negative") -> Positive | T67: 134.079 | U67: pop, Dance/Electronic
A68: 542 | B68: =_xlfn.xlookup(A68, artists!A$2:A$836, artists!B$2:B$836) -> Avicii | C68: Waiting For Love | D68: 230613 | E68: =D68/1000 -> 230.613 | F68: =FALSE() -> FALSE | G68: 18 | H68: =_xlfn.xlookup(G68, years!A$2:A$836, years!B$2:B$836) -> 2015 | I68: 79 | J68: 0.579 | K68: 0.736 | L68: =IF(K68>0.66,"High",IF(K68>0.33&K68<=0.66,"Medium","Low")) -> High | M68: -3.863 | N68: 0.0527 | O68: 0.31 | P68: 0 | Q68: 0.198 | R68: 0.613 | S68: =IF(R68 >= 0.5, "Positive", "Negative") -> Positive | T68: 127.999 | U68: pop, Dance/Electronic
A69: 744 | B69: =_xlfn.xlookup(A69, artists!A$2:A$836, artists!B$2:B$836) -> The Vamps | C69: All Night | D69: 197640 | E69: =D69/1000 -> 197.64 | F69: =FALSE() -> FALSE | G69: 20 | H69: =_xlfn.xlookup(G69, years!A$2:A$836, years!B$2:B$836) -> 2017 | I69: 73 | J69: 0.538 | K69: 0.804 | L69: =IF(K69>0.66,"High",IF(K69>0.33&K69<=0.66,"Medium","Low")) -> High | M69: -5.194 | N69: 0.0358 | O69: 0.0041 | P69: 0 | Q69: 0.33 | R69: 0.507 | S69: =IF(R69 >= 0.5, "Positive", "Negative") -> Positive | T69: 144.992 | U69: pop
A70: 433 | B70: =_xlfn.xlookup(A70, artists!A$2:A$836, artists!B$2:B$836) -> John Legend | C70: All of Me | D70: 269560 | E70: =D70/1000 -> 269.56 | F70: =FALSE() -> FALSE | G70: 16 | H70: =_xlfn.xlookup(G70, years!A$2:A$836, years!B$2:B$836) -> 2013 | I70: 84 | J70: 0.422 | K70: 0.264 | L70: =IF(K70>0.66,"High",IF(K70>0.33&K70<=0.66,"Medium","Low")) -> Low | M70: -7.064 | N70: 0.0322 | O70: 0.922 | P70: 0 | Q70: 0.132 | R70: 0.331 | S70: =IF(R70 >= 0.5, "Positive", "Negative") -> Negative | T70: 119.93 | U70: pop, R&B
A71: 269 | B71: =_xlfn.xlookup(A71, artists!A$2:A$836, artists!B$2:B$836) -> Kanye West | C71: All Of The Lights | D71: 299613 | E71: =D71/1000 -> 299.613 | F71: =TRUE() -> TRUE | G71: 13 | H71: =_xlfn.xlookup(G71, years!A$2:A$836, years!B$2:B$836) -> 2010 | I71: 76 | J71: 0.531 | K71: 0.803 | L71: =IF(K71>0.66,"High",IF(K71>0.33&K71<=0.66,"Medium","Low")) -> High | M71: -3.284 | N71: 0.0717 | O71: 0.0796 | P71: 1.71e-05 | Q71: 0.176 | R71: 0.221 | S71: =IF(R71 >= 0.5, "Positive", "Negative") -> Negative | T71: 142.113 | U71: hip hop
A72: 192 | B72: =_xlfn.xlookup(A72, artists!A$2:A$836, artists!B$2:B$836) -> Beyoncé | C72: Me, Myself and I | D72: 301133 | E72: =D72/1000 -> 301.133 | F72: =FALSE() -> FALSE | G72: 6 | H72: =_xlfn.xlookup(G72, years!A$2:A$836, years!B$2:B$836) -> 2003 | I72: 62 | J72: 0.75 | K72: 0.458 | L72: =IF(K72>0.66,"High",IF(K72>0.33&K72<=0.66,"Medium","Low")) -> Low | M72: -9.092 | N72: 0.0803 | O72: 0.226 | P72: 3.25e-05 | Q72: 0.137 | R72: 0.536 | S72: =IF(R72 >= 0.5, "Positive", "Negative") -> Positive | T72: 83.61 | U72: pop, R&B
A73: 425 | B73: =_xlfn.xlookup(A73, artists!A$2:A$836, artists!B$2:B$836) -> OneRepublic | C73: All The Right Moves | D73: 238000 | E73: =D73/1000 -> 238 | F73: =FALSE() -> FALSE | G73: 12 | H73: =_xlfn.xlookup(G73, years!A$2:A$836, years!B$2:B$836) -> 2009 | I73: 65 | J73: 0.529 | K73: 0.948 | L73: =IF(K73>0.66,"High",IF(K73>0.33&K73<=0.66,"Medium","Low")) -> High | M73: -3.527 | N73: 0.0474 | O73: 0.258 | P73: 9.35e-06 | Q73: 0.283 | R73: 0.65 | S73: =IF(R73 >= 0.5, "Positive", "Negative") -> Positive | T73: 146.024 | U73: pop
A74: 173 | B74: =_xlfn.xlookup(A74, artists!A$2:A$836, artists!B$2:B$836) -> Big Brovaz | C74: Nu Flow | D74: 201480 | E74: =D74/1000 -> 201.48 | F74: =FALSE() -> FALSE | G74: 4 | H74: =_xlfn.xlookup(G74, years!A$2:A$836, years!B$2:B$836) -> 2001 | I74: 45 | J74: 0.783 | K74: 0.726 | L74: =IF(K74>0.66,"High",IF(K74>0.33&K74<=0.66,"Medium","Low")) -> High | M74: -8.718 | N74: 0.106 | O74: 0.0903 | P74: 2.53e-06 | Q74: 0.363 | R74: 0.784 | S74: =IF(R74 >= 0.5, "Positive", "Negative") -> Positive | T74: 148.062 | U74: pop
A75: 539 | B75: =_xlfn.xlookup(A75, artists!A$2:A$836, artists!B$2:B$836) -> Kendrick Lamar | C75: All The Stars (with SZA) | D75: 232186 | E75: =D75/1000 -> 232.186 | F75: =TRUE() -> TRUE | G75: 21 | H75: =_xlfn.xlookup(G75, years!A$2:A$836, years!B$2:B$836) -> 2018 | I75: 80 | J75: 0.698 | K75: 0.633 | L75: =IF(K75>0.66,"High",IF(K75>0.33&K75<=0.66,"Medium","Low")) -> Low | M75: -4.946 | N75: 0.0597 | O75: 0.0605 | P75: 0.000194 | Q75: 0.0926 | R75: 0.552 | S75: =IF(R75 >= 0.5, "Positive", "Negative") -> Positive | T75: 96.924 | U75: hip hop
A76: 195 | B76: =_xlfn.xlookup(A76, artists!A$2:A$836, artists!B$2:B$836) -> t.A.T.u. | C76: All The Things She Said | D76: 214440 | E76: =D76/1000 -> 214.44 | F76: =TRUE() -> TRUE | G76: 23 | H76: =_xlfn.xlookup(G76, years!A$2:A$836, years!B$2:B$836) -> 2020 | I76: 39 | J76: 0.527 | K76: 0.834 | L76: =IF(K76>0.66,"High",IF(K76>0.33&K76<=0.66,"Medium","Low")) -> High | M76: -5.767 | N76: 0.0474 | O76: 0.0411 | P76: 0.00599 | Q76: 0.105 | R76: 0.381 | S76: =IF(R76 >= 0.5, "Positive", "Negative") -> Negative | T76: 179.92 | U76: pop
A77: 497 | B77: =_xlfn.xlookup(A77, artists!A$2:A$836, artists!B$2:B$836) -> The Wanted | C77: All Time Low | D77: 205200 | E77: =D77/1000 -> 205.2 | F77: =FALSE() -> FALSE | G77: 13 | H77: =_xlfn.xlookup(G77, years!A$2:A$836, years!B$2:B$836) -> 2010 | I77: 18 | J77: 0.689 | K77: 0.615 | L77: =IF(K77>0.66,"High",IF(K77>0.33&K77<=0.66,"Medium","Low")) -> Low | M77: -5.022 | N77: 0.0563 | O77: 0.352 | P77: 0 | Q77: 0.0789 | R77: 0.783 | S77: =IF(R77 >= 0.5, "Positive", "Negative") -> Positive | T77: 134.036 | U77: pop, Dance/Electronic
A78: 691 | B78: =_xlfn.xlookup(A78, artists!A$2:A$836, artists!B$2:B$836) -> Jon Bellion | C78: All Time Low | D78: 217603 | E78: =D78/1000 -> 217.603 | F78: =TRUE() -> TRUE | G78: 19 | H78: =_xlfn.xlookup(G78, years!A$2:A$836, years!B$2:B$836) -> 2016 | I78: 70 | J78: 0.617 | K78: 0.567 | L78: =IF(K78>0.66,"High",IF(K78>0.33&K78<=0.66,"Medium","Low")) -> Low | M78: -4.188 | N78: 0.0828 | O78: 0.0584 | P78: 0 | Q78: 0.0933 | R78: 0.505 | S78: =IF(R78 >= 0.5, "Positive", "Negative") -> Positive | T78: 90.246 | U78: hip hop, pop
A79: 190 | B79: =_xlfn.xlookup(A79, artists!A$2:A$836, artists!B$2:B$836) -> Michelle Branch | C79: All You Wanted | D79: 217680 | E79: =D79/1000 -> 217.68 | F79: =FALSE() -> FALSE | G79: 4 | H79: =_xlfn.xlookup(G79, years!A$2:A$836, years!B$2:B$836) -> 2001 | I79: 60 | J79: 0.499 | K79: 0.72 | L79: =IF(K79>0.66,"High",IF(K79>0.33&K79<=0.66,"Medium","Low")) -> High | M79: -9.101 | N79: 0.0286 | O79: 0.00466 | P79: 0.00303 | Q79: 0.122 | R79: 0.652 | S79: =IF(R79 >= 0.5, "Positive", "Negative") -> Positive | T79: 96.103 | U79: pop, Folk/Acoustic
A80: 298 | B80: =_xlfn.xlookup(A80, artists!A$2:A$836, artists!B$2:B$836) -> Brian McFadden | C80: Almost Here | D80: 229826 | E80: =D80/1000 -> 229.826 | F80: =FALSE() -> FALSE | G80: 7 | H80: =_xlfn.xlookup(G80, years!A$2:A$836, years!B$2:B$836) -> 2004 | I80: 42 | J80: 0.561 | K80: 0.452 | L80: =IF(K80>0.66,"High",IF(K80>0.33&K80<=0.66,"Medium","Low")) -> Low | M80: -7.324 | N80: 0.0336 | O80: 0.409 | P80: 0 | Q80: 0.106 | R80: 0.316 | S80: =IF(R80 >= 0.5, "Positive", "Negative") -> Negative | T80: 77.984 | U80: set()
A81: 675 | B81: =_xlfn.xlookup(A81, artists!A$2:A$836, artists!B$2:B$836) -> Shawn Mendes | C81: Stitches | D81: 206880 | E81: =D81/1000 -> 206.88 | F81: =FALSE() -> FALSE | G81: 18 | H81: =_xlfn.xlookup(G81, years!A$2:A$836, years!B$2:B$836) -> 2015 | I81: 78 | J81: 0.746 | K81: 0.754 | L81: =IF(K81>0.66,"High",IF(K81>0.33&K81<=0.66,"Medium","Low")) -> High | M81: -6.684 | N81: 0.0676 | O81: 0.0152 | P81: 0 | Q81: 0.0486 | R81: 0.746 | S81: =IF(R81 >= 0.5, "Positive", "Negative") -> Positive | T81: 149.882 | U81: pop
A82: 470 | B82: =_xlfn.xlookup(A82, artists!A$2:A$836, artists!B$2:B$836) -> Stromae | C82: Alors on danse - Radio Edit | D82: 206066 | E82: =D82/1000 -> 206.066 | F82: =FALSE() -> FALSE | G82: 13 | H82: =_xlfn.xlookup(G82, years!A$2:A$836, years!B$2:B$836) -> 2010 | I82: 77 | J82: 0.791 | K82: 0.59 | L82: =IF(K82>0.66,"High",IF(K82>0.33&K82<=0.66,"Medium","Low")) -> Low | M82: -9.206 | N82: 0.0793 | O82: 0.0994 | P82: 0.00203 | Q82: 0.065 | R82: 0.714 | S82: =IF(R82 >= 0.5, "Positive", "Negative") -> Positive | T82: 119.951 | U82: pop
A83: 230 | B83: =_xlfn.xlookup(A83, artists!A$2:A$836, artists!B$2:B$836) -> Kelly Clarkson | C83: Already Gone | D83: 281560 | E83: =D83/1000 -> 281.56 | F83: =FALSE() -> FALSE | G83: 12 | H83: =_xlfn.xlookup(G83, years!A$2:A$836, years!B$2:B$836) -> 2009 | I83: 56 | J83: 0.209 | K83: 0.872 | L83: =IF(K83>0.66,"High",IF(K83>0.33&K83<=0.66,"Medium","Low")) -> High | M83: -2.996 | N83: 0.0757 | O83: 0.217 | P83: 0 | Q83: 0.0768 | R83: 0.294 | S83: =IF(R83 >= 0.5, "Positive", "Negative") -> Negative | T83: 78.139 | U83: pop, R&B
A84: 132 | B84: =_xlfn.xlookup(A84, artists!A$2:A$836, artists!B$2:B$836) -> Ja Rule | C84: Always On Time | D84: 245133 | E84: =D84/1000 -> 245.133 | F84: =TRUE() -> TRUE | G84: 4 | H84: =_xlfn.xlookup(G84, years!A$2:A$836, years!B$2:B$836) -> 2001 | I84: 73 | J84: 0.839 | K84: 0.706 | L84: =IF(K84>0.66,"High",IF(K84>0.33&K84<=0.66,"Medium","Low")) -> High | M84: -6.104 | N84: 0.199 | O84: 0.208 | P84: 0 | Q84: 0.242 | R84: 0.839 | S84: =IF(R84 >= 0.5, "Positive", "Negative") -> Positive | T84: 96.673 | U84: hip hop, pop, R&B
A85: 616 | B85: =_xlfn.xlookup(A85, artists!A$2:A$836, artists!B$2:B$836) -> Nico & Vinz | C85: Am I Wrong | D85: 245866 | E85: =D85/1000 -> 245.866 | F85: =FALSE() -> FALSE | G85: 17 | H85: =_xlfn.xlookup(G85, years!A$2:A$836, years!B$2:B$836) -> 2014 | I85: 76 | J85: 0.729 | K85: 0.675 | L85: =IF(K85>0.66,"High",IF(K85>0.33&K85<=0.66,"Medium","Low")) -> High | M85: -6.003 | N85: 0.0312 | O85: 0.175 | P85: 1.58e-06 | Q85: 0.55 | R85: 0.779 | S85: =IF(R85 >= 0.5, "Positive", "Negative") -> Positive | T85: 119.968 | U85: hip hop, pop
A86: 108 | B86: =_xlfn.xlookup(A86, artists!A$2:A$836, artists!B$2:B$836) -> Christina Milian | C86: AM To PM | D86: 231213 | E86: =D86/1000 -> 231.213 | F86: =FALSE() -> FALSE | G86: 4 | H86: =_xlfn.xlookup(G86, years!A$2:A$836, years!B$2:B$836) -> 2001 | I86: 60 | J86: 0.872 | K86: 0.868 | L86: =IF(K86>0.66,"High",IF(K86>0.33&K86<=0.66,"Medium","Low")) -> High | M86: -3.036 | N86: 0.12 | O86: 0.153 | P86: 2.26e-05 | Q86: 0.843 | R86: 0.822 | S86: =IF(R86 >= 0.5, "Positive", "Negative") -> Positive | T86: 105.005 | U86: hip hop, pop, R&B
A87: 252 | B87: =_xlfn.xlookup(A87, artists!A$2:A$836, artists!B$2:B$836) -> George Michael | C87: Amazing | D87: 265826 | E87: =D87/1000 -> 265.826 | F87: =FALSE() -> FALSE | G87: 7 | H87: =_xlfn.xlookup(G87, years!A$2:A$836, years!B$2:B$836) -> 2004 | I87: 57 | J87: 0.805 | K87: 0.754 | L87: =IF(K87>0.66,"High",IF(K87>0.33&K87<=0.66,"Medium","Low")) -> High | M87: -6.825 | N87: 0.0394 | O87: 0.0884 | P87: 1.77e-06 | Q87: 0.117 | R87: 0.88 | S87: =IF(R87 >= 0.5, "Positive", "Negative") -> Positive | T87: 128.429 | U87: set()
A88: 352 | B88: =_xlfn.xlookup(A88, artists!A$2:A$836, artists!B$2:B$836) -> Razorlight | C88: America | D88: 249760 | E88: =D88/1000 -> 249.76 | F88: =FALSE() -> FALSE | G88: 9 | H88: =_xlfn.xlookup(G88, years!A$2:A$836, years!B$2:B$836) -> 2006 | I88: 67 | J88: 0.447 | K88: 0.568 | L88: =IF(K88>0.66,"High",IF(K88>0.33&K88<=0.66,"Medium","Low")) -> Low | M88: -4.975 | N88: 0.0305 | O88: 0.295 | P88: 3.26e-06 | Q88: 0.355 | R88: 0.149 | S88: =IF(R88 >= 0.5, "Positive", "Negative") -> Negative | T88: 90.933 | U88: rock, pop
A89: 412 | B89: =_xlfn.xlookup(A89, artists!A$2:A$836, artists!B$2:B$836) -> Estelle | C89: American Boy | D89: 284733 | E89: =D89/1000 -> 284.733 | F89: =TRUE() -> TRUE | G89: 11 | H89: =_xlfn.xlookup(G89, years!A$2:A$836, years!B$2:B$836) -> 2008 | I89: 78 | J89: 0.727 | K89: 0.729 | L89: =IF(K89>0.66,"High",IF(K89>0.33&K89<=0.66,"Medium","Low")) -> High | M89: -2.99 | N89: 0.326 | O89: 0.171 | P89: 0 | Q89: 0.07 | R89: 0.512 | S89: =IF(R89 >= 0.5, "Positive", "Negative") -> Positive | T89: 117.932 | U89: R&B
A90: 271 | B90: =_xlfn.xlookup(A90, artists!A$2:A$836, artists!B$2:B$836) -> Green Day | C90: American Idiot | D90: 176346 | E90: =D90/1000 -> 176.346 | F90: =TRUE() -> TRUE | G90: 7 | H90: =_xlfn.xlookup(G90, years!A$2:A$836, years!B$2:B$836) -> 2004 | I90: 77 | J90: 0.38 | K90: 0.988 | L90: =IF(K90>0.66,"High",IF(K90>0.33&K90<=0.66,"Medium","Low")) -> High | M90: -2.042 | N90: 0.0639 | O90: 2.64e-05 | P90: 7.86e-05 | Q90: 0.368 | R90: 0.769 | S90: =IF(R90 >= 0.5, "Positive", "Negative") -> Positive | T90: 186.113 | U90: rock
A91: 31 | B91: =_xlfn.xlookup(A91, artists!A$2:A$836, artists!B$2:B$836) -> Madonna | C91: American Pie | D91: 273533 | E91: =D91/1000 -> 273.533 | F91: =FALSE() -> FALSE | G91: 3 | H91: =_xlfn.xlookup(G91, years!A$2:A$836, years!B$2:B$836) -> 2000 | I91: 58 | J91: 0.631 | K91: 0.734 | L91: =IF(K91>0.66,"High",IF(K91>0.33&K91<=0.66,"Medium","Low")) -> High | M91: -7.48 | N91: 0.036 | O91: 0.348 | P91: 0 | Q91: 0.135 | R91: 0.591 | S91: =IF(R91 >= 0.5, "Positive", "Negative") -> Positive | T91: 124.036 | U91: pop
A92: 526 | B92: =_xlfn.xlookup(A92, artists!A$2:A$836, artists!B$2:B$836) -> Nicki Minaj | C92: Anaconda | D92: 260240 | E92: =D92/1000 -> 260.24 | F92: =TRUE() -> TRUE | G92: 17 | H92: =_xlfn.xlookup(G92, years!A$2:A$836, years!B$2:B$836) -> 2014 | I92: 66 | J92: 0.964 | K92: 0.605 | L92: =IF(K92>0.66,"High",IF(K92>0.33&K92<=0.66,"Medium","Low")) -> Low | M92: -6.223 | N92: 0.179 | O92: 0.0668 | P92: 7.78e-06 | Q92: 0.214 | R92: 0.646 | S92: =IF(R92 >= 0.5, "Positive", "Negative") -> Positive | T92: 129.994 | U92: hip hop, pop
A93: 222 | B93: =_xlfn.xlookup(A93, artists!A$2:A$836, artists!B$2:B$836) -> Amanda Perez | C93: Angel | D93: 218760 | E93: =D93/1000 -> 218.76 | F93: =FALSE() -> FALSE | G93: 6 | H93: =_xlfn.xlookup(G93, years!A$2:A$836, years!B$2:B$836) -> 2003 | I93: 48 | J93: 0.638 | K93: 0.54 | L93: =IF(K93>0.66,"High",IF(K93>0.33&K93<=0.66,"Medium","Low")) -> Low | M93: -6.849 | N93: 0.0473 | O93: 0.506 | P93: 0 | Q93: 0.157 | R93: 0.352 | S93: =IF(R93 >= 0.5, "Positive", "Negative") -> Negative | T93: 143.772 | U93: pop, R&B
A94: 505 | B94: =_xlfn.xlookup(A94, artists!A$2:A$836, artists!B$2:B$836) -> Neon Trees | C94: Animal | D94: 212306 | E94: =D94/1000 -> 212.306 | F94: =FALSE() -> FALSE | G94: 13 | H94: =_xlfn.xlookup(G94, years!A$2:A$836, years!B$2:B$836) -> 2010 | I94: 64 | J94: 0.482 | K94: 0.829 | L94: =IF(K94>0.66,"High",IF(K94>0.33&K94<=0.66,"Medium","Low")) -> High | M94: -5.576 | N94: 0.0437 | O94: 0.00034 | P94: 0 | Q94: 0.378 | R94: 0.739 | S94: =IF(R94 >= 0.5, "Positive", "Negative") -> Positive | T94: 147.99 | U94: rock, pop
A95: 236 | B95: =_xlfn.xlookup(A95, artists!A$2:A$836, artists!B$2:B$836) -> Maroon 5 | C95: Animals | D95: 231013 | E95: =D95/1000 -> 231.013 | F95: =FALSE() -> FALSE | G95: 17 | H95: =_xlfn.xlookup(G95, years!A$2:A$836, years!B$2:B$836) -> 2014 | I95: 79 | J95: 0.279 | K95: 0.742 | L95: =IF(K95>0.66,"High",IF(K95>0.33&K95<=0.66,"Medium","Low")) -> High | M95: -6.46 | N95: 0.0898 | O95: 0.000185 | P95: 0 | Q95: 0.593 | R95: 0.328 | S95: =IF(R95 >= 0.5, "Positive", "Negative") -> Negative | T95: 189.868 | U95: pop
A96: 577 | B96: =_xlfn.xlookup(A96, artists!A$2:A$836, artists!B$2:B$836) -> Martin Garrix | C96: Animals - Radio Edit | D96: 176117 | E96: =D96/1000 -> 176.117 | F96: =FALSE() -> FALSE | G96: 16 | H96: =_xlfn.xlookup(G96, years!A$2:A$836, years!B$2:B$836) -> 2013 | I96: 0 | J96: 0.593 | K96: 0.914 | L96: =IF(K96>0.66,"High",IF(K96>0.33&K96<=0.66,"Medium","Low")) -> High | M96: -5.351 | N96: 0.0363 | O96: 0.00137 | P96: 0.445 | Q96: 0.0714 | R96: 0.0381 | S96: =IF(R96 >= 0.5, "Positive", "Negative") -> Negative | T96: 128.015 | U96: pop, Dance/Electronic
A97: 109 | B97: =_xlfn.xlookup(A97, artists!A$2:A$836, artists!B$2:B$836) -> Roger Sanchez | C97: Another Chance | D97: 452906 | E97: =D97/1000 -> 452.906 | F97: =FALSE() -> FALSE | G97: 3 | H97: =_xlfn.xlookup(G97, years!A$2:A$836, years!B$2:B$836) -> 2000 | I97: 50 | J97: 0.61 | K97: 0.82 | L97: =IF(K97>0.66,"High",IF(K97>0.33&K97<=0.66,"Medium","Low")) -> High | M97: -10.029 | N97: 0.0312 | O97: 0.000211 | P97: 0.146 | Q97: 0.138 | R97: 0.45 | S97: =IF(R97 >= 0.5, "Positive", "Negative") -> Negative | T97: 127.993 | U97: Dance/Electronic
A98: 192 | B98: =_xlfn.xlookup(A98, artists!A$2:A$836, artists!B$2:B$836) -> Beyoncé | C98: Naughty Girl | D98: 208600 | E98: =D98/1000 -> 208.6 | F98: =FALSE() -> FALSE | G98: 6 | H98: =_xlfn.xlookup(G98, years!A$2:A$836, years!B$2:B$836) -> 2003 | I98: 63 | J98: 0.735 | K98: 0.466 | L98: =IF(K98>0.66,"High",IF(K98>0.33&K98<=0.66,"Medium","Low")) -> Low | M98: -8.65 | N98: 0.0857 | O98: 0.239 | P98: 6.24e-06 | Q98: 0.102 | R98: 0.643 | S98: =IF(R98 >= 0.5, "Positive", "Negative") -> Positive | T98: 99.973 | U98: pop, R&B
A99: 575 | B99: =_xlfn.xlookup(A99, artists!A$2:A$836, artists!B$2:B$836) -> Tom Odell | C99: Another Love | D99: 244360 | E99: =D99/1000 -> 244.36 | F99: =TRUE() -> TRUE | G99: 16 | H99: =_xlfn.xlookup(G99, years!A$2:A$836, years!B$2:B$836) -> 2013 | I99: 88 | J99: 0.445 | K99: 0.537 | L99: =IF(K99>0.66,"High",IF(K99>0.33&K99<=0.66,"Medium","Low")) -> Low | M99: -8.532 | N99: 0.04 | O99: 0.695 | P99: 1.65e-05 | Q99: 0.0944 | R99: 0.131 | S99: =IF(R99 >= 0.5, "Positive", "Negative") -> Negative | T99: 122.769 | U99: pop
A100: 410 | B100: =_xlfn.xlookup(A100, artists!A$2:A$836, artists!B$2:B$836) -> Jack White | C100: Another Way to Die | D100: 262240 | E100: =D100/1000 -> 262.24 | F100: =FALSE() -> FALSE | G100: 10 | H100: =_xlfn.xlookup(G100, years!A$2:A$836, years!B$2:B$836) -> 2007 | I100: 56 | J100: 0.486 | K100: 0.765 | L100: =IF(K100>0.66,"High",IF(K100>0.33&K100<=0.66,"Medium","Low")) -> High | M100: -4.23 | N100: 0.128 | O100: 0.0239 | P100: 3.02e-05 | Q100: 0.11 | R100: 0.386 | S100: =IF(R100 >= 0.5, "Positive", "Negative") -> Negative | T100: 141.933 | U100: rock, blues
...

Sheet artists
A1: artist_id | B1: artist_name
A2: 1 | B2: Britney Spears
A3: 2 | B3: blink-182
A4: 3 | B4: Faith Hill
A5: 4 | B5: Bon Jovi
A6: 5 | B6: *NSYNC
A7: 6 | B7: Sisqo
A8: 7 | B8: Eminem
A9: 8 | B9: Robbie Williams
A10: 9 | B10: Destiny's Child
A11: 10 | B11: Modjo
A12: 11 | B12: Gigi D'Agostino
A13: 12 | B13: Eiffel 65
... A836: 835 | B836: Blanco Brown

Sheet years
A1: year_id | B1: year
A2: 1 | B2: 1998
A3: 2 | B3: 1999
A4: 3 | B4: 2000
A5: 4 | B5: 2001
A6: 5 | B6: 2002
A7: 6 | B7: 2003
A8: 7 | B8: 2004
A9: 8 | B9: 2005
A10: 9 | B10: 2006
A11: 10 | B11: 2007
A12: 11 | B12: 2008
A13: 12 | B13: 2009
... A24: 23 | B24: 2020

Sheet null_values
B1: artist_id | C1: song | D1: duration_ms | E1: explicit | F1: year_id | G1: popularity | H1: danceability | I1: energy | J1: loudness | K1: speechiness | L1: acousticness | M1: instrumentalness | N1: liveness | O1: valence | P1: tempo | Q1: genre
A2: Number of null values | B2: =COUNTBLANK(songs!A$2:A$2004) -> 61 | C2: =COUNTBLANK(songs!C$2:C$2004) -> 61 | D2: =COUNTBLANK(songs!D$2:D$2004) -> 61 | E2: =COUNTBLANK(songs!F$2:F$2004) -> 61 | F2: =COUNTBLANK(songs!G$2:G$2004) -> 61 | G2: =COUNTBLANK(songs!I$2:I$2004) -> 61 | H2: =COUNTBLANK(songs!J$2:J$2004) -> 61 | I2: =COUNTBLANK(songs!K$2:K$2004) -> 61 | J2: =COUNTBLANK(songs!M$2:M$2004) -> 61 | K2: =COUNTBLANK(songs!N$2:N$2004) -> 61 | L2: =COUNTBLANK(songs!O$2:O$2004) -> 61 | M2: =COUNTBLANK(songs!P$2:P$2004) -> 61 | N2: =COUNTBLANK(songs!Q$2:Q$2004) -> 61 | O2: =COUNTBLANK(songs!R$2:R$2004) -> 61 | P2: =COUNTBLANK(songs!T$2:T$2004) -> 61 | Q2: =COUNTBLANK(songs!U$2:U$2004) -> 61

Sheet EDA
B1: STATISTICS | M1: # OF UNIQUE VALUES
B2: duration_ms | C2: duration_seconds | D2: popularity | E2: danceability | F2: energy | G2: loudness | H2: speechiness | I2: acousticness | J2: instrumentalness | M2: artist_name | N2: song
A3: Count (number of records) | B3: =COUNT(songs!D$2:D$1943) -> 1942 | C3: =COUNT(songs!E$2:E$1943) -> 1942 | D3: =COUNT(songs!I$2:I$1943) -> 1942 | E3: =COUNT(songs!J$2:J$1943) -> 1942 | F3: =COUNT(songs!K$2:K$1943) -> 1942 | G3: =COUNT(songs!M$2:M$1943) -> 1942 | H3: =COUNT(songs!N$2:N$1943) -> 1942 | I3: =COUNT(songs!O$2:O$1943) -> 1942 | J3: =COUNT(songs!P$2:P$1943) -> 1942 | L3: Number of unique values | M3: =COUNTA(_xlfn.unique(songs!B$2:B$1943)) -> 835 | N3: =COUNTA(_xlfn.unique(songs!C$2:C$1943)) -> 1874
A4: Average | B4: =AVERAGE(songs!D$2:D$1943) -> 228644.26 | C4: =AVERAGE(songs!E$2:E$1943) -> 228.64426 | D4: =AVERAGE(songs!I$2:I$1943) -> 59.637487 | E4: =AVERAGE(songs!J$2:J$1943) -> 0.66780381 | F4: =AVERAGE(songs!K$2:K$1943) -> 0.72156797 | G4: =AVERAGE(songs!M$2:M$1943) -> -5.513465 | H4: =AVERAGE(songs!N$2:N$1943) -> 0.10388671 | I4: =AVERAGE(songs!O$2:O$1943) -> 0.12811396 | J4: =AVERAGE(songs!P$2:P$1943) -> 0.01536456
A5: Median | B5: =MEDIAN(songs!D$2:D$1943) -> 223219.5 | C5: =MEDIAN(songs!E$2:E$1943) -> 223.2195 | D5: =MEDIAN(songs!I$2:I$1943) -> 65 | E5: =MEDIAN(songs!J$2:J$1943) -> 0.676 | F5: =MEDIAN(songs!K$2:K$1943) -> 0.739 | G5: =MEDIAN(songs!M$2:M$1943) -> -5.2845 | H5: =MEDIAN(songs!N$2:N$1943) -> 0.061 | I5: =MEDIAN(songs!O$2:O$1943) -> 0.0557 | J5: =MEDIAN(songs!P$2:P$1943) -> 0
A6: First quartile | B6: =QUARTILE(songs!D$2:D$1943, 1) -> 203506 | C6: =QUARTILE(songs!E$2:E$1943, 1) -> 203.506 | D6: =QUARTILE(songs!I$2:I$1943, 1) -> 56 | E6: =QUARTILE(songs!J$2:J$1943, 1) -> 0.581 | F6: =QUARTILE(songs!K$2:K$1943, 1) -> 0.624 | G6: =QUARTILE(songs!M$2:M$1943, 1) -> -6.4895 | H6: =QUARTILE(songs!N$2:N$1943, 1) -> 0.0397 | I6: =QUARTILE(songs!O$2:O$1943, 1) -> 0.013525 | J6: =QUARTILE(songs!P$2:P$1943, 1) -> 0
A7: Minimum | B7: =MIN(songs!D$2:D$1943) -> 113000 | C7: =MIN(songs!E$2:E$1943) -> 113 | D7: =MIN(songs!I$2:I$1943) -> 0 | E7: =MIN(songs!J$2:J$1943) -> 0.129 | F7: =MIN(songs!K$2:K$1943) -> 0.0549 | G7: =MIN(songs!M$2:M$1943) -> -20.514 | H7: =MIN(songs!N$2:N$1943) -> 0.0232 | I7: =MIN(songs!O$2:O$1943) -> 1.92e-05 | J7: =MIN(songs!P$2:P$1943) -> 0

Sheet pivot_tables
H2: ARTIST WITH THE HIGHEST NUMBER OF SONGS | K2: Artist | L2: % of negative songs | M2: % of positive songs
A3: year | B3: Average of tempo | H3: Drake | I3: 23 | K3: Drake | L3: 0.60869565 | M3: 0.39130435
A4: 1998 | B4: 81.125 | H4: Rihanna | I4: 23 | K4: Rihanna | L4: 0.39130435 | M4: 0.60869565
A5: 1999 | B5: 122.705 | H5: Eminem | I5: 21 | K5: Eminem | L5: 0.33333333 | M5: 0.66666667
A6: 2000 | B6: 112.66087 | H6: Calvin Harris | I6: 20 | K6: Calvin Harris | L6: 0.25 | M6: 0.75
A7: 2001 | B7: 117.41488 | H7: Britney Spears | I7: 19 | K7: Britney Spears | L7: 0.26315789 | M7: 0.73684211
A8: 2002 | B8: 113.13156 | H8: David Guetta | I8: 18 | K8: David Guetta | L8: 0.55555556 | M8: 0.44444444
A9: 2003 | B9: 119.41037 | H9: Beyoncé | I9: 16 | K9: Beyoncé | L9: 0.5 | M9: 0.5
A10: 2004 | B10: 115.00748 | H10: Chris Brown | I10: 16 | K10: Chris Brown | L10: 0.375 | M10: 0.625
A11: 2005 | B11: 119.28991 | H11: Kanye West | I11: 16 | K11: Kanye West | L11: 0.625 | M11: 0.375
A12: 2006 | B12: 113.86545 | H12: Katy Perry | I12: 16 | K12: Katy Perry | L12: 0.3125 | M12: 0.6875
A13: 2007 | B13: 120.7118 | H13: Taylor Swift | I13: 16 | K13: Taylor Swift | L13: 0.5625 | M13: 0.4375
A14: 2008 | B14: 125.71456 | H14: Black Eyed Peas | I14: 14 | K14: Black Eyed Peas | L14: 0.35714286 | M14: 0.64285714
A15: 2009 | B15: 125.2184 | H15: P!nk | I15: 14 | K15: P!nk | L15: 0.28571429 | M15: 0.71428571
... A22: 2016 | B22: 120.88265 | H22: Jason Derulo | I22: 11 | K22: Jason Derulo | L22: 0.090909091 | M22: 0.90909091
A23: 2017 | B23: 120.04531 | K23: Usher | L23: 0.27272727 | M23: 0.72727273
A24: 2018 | B24: 118.66576 | K24: Nelly | L24: 0.18181818 | M24: 0.81818182
A25: 2019 | B25: 127.95299 | K25: Avril Lavigne | L25: 0.6 | M25: 0.4
A26: 2020 | B26: 128.143 | K26: Avicii | L26: 0.5 | M26: 0.5
A27: Total Result | B27: 120.14085 | K27: Flo Rida | L27: 0.3 | M27: 0.7
H28: AVERAGE TEMPO BY RELEASE YEAR OF SONG
H29: Year | I29: Average tempo (BPM)
H30: 1998 | I30: 81.125
H31: 1999 | I31: 122.705
H32: 2000 | I32: 112.66087
H33: 2001 | I33: 117.41488
H34: 2002 | I34: 113.13156
H35: 2003 | I35: 119.41037
H36: 2004 | I36: 115.00748
H37: 2005 | I37: 119.28991
H38: 2006 | I38: 113.86545
H39: 2007 | I39: 120.7118
H40: 2008 | I40: 125.71456
H41: 2009 | I41: 125.2184
... H52: 2020 | I52: 128.143
